LICENSE
README.md
setup.cfg
setup.py
nextcord/ext/space/__init__.py
nextcord/ext/space/client.py
nextcord/ext/space/config.py
nextcord/ext/space/dawn.py
nextcord/ext/space/flags.py
nextcord/ext/space/gateway.py
nextcord/ext/space/http.py
nextcord/ext/space/op.py
nextcord/ext/space/recorders/base.py
nextcord/ext/space/recorders/databases.py
nextcord_ext_space.egg-info/PKG-INFO
nextcord_ext_space.egg-info/SOURCES.txt
nextcord_ext_space.egg-info/dependency_links.txt
nextcord_ext_space.egg-info/requires.txt
nextcord_ext_space.egg-info/top_level.txt