Metadata-Version: 2.1
Name: nextcord-ext-space
Version: 0.1.0
Summary: A event logger for nextcord discord API library.
Home-page: https://github.com/japandotorg/nextcord-ext-space
Author: japandotorg
License: MIT
Keywords: nextcord,extension,discord
Platform: UNKNOWN
Classifier: License :: OSI Approved :: MIT License
Classifier: Development Status :: 4 - Beta
Classifier: Intended Audience :: Developers
Classifier: Natural Language :: English
Classifier: Operating System :: OS Independent
Classifier: Programming Language :: Python :: 3.8
Classifier: Programming Language :: Python :: 3.9
Classifier: Topic :: Internet
Classifier: Topic :: Software Development :: Libraries
Classifier: Topic :: Software Development :: Libraries :: Python Modules
Classifier: Topic :: Utilities
Requires-Python: >=3.8.0
License-File: LICENSE
